[
  {
    "name": "Lassalyckans Skidstadion",
    "municipality": "Ulricehamn",
    "lat": 57.7907,
    "lon": 13.4189,
    "status": "Troligen öppet",
    "snow_depth": "17 cm",
    "temperature": "-5°C",
    "last_update": "2026-01-09 17:03",
    "weather": "☀️ Klart",
    "forecast": {
      "dates": [
        "2026-01-09",
        "2026-01-10",
        "2026-01-11",
        "2026-01-12",
        "2026-01-13",
        "2026-01-14",
        "2026-01-15"
      ],
      "max_temp": [
        -4.1,
        -6.1,
        -6.0,
        -5.7,
        -1.9,
        0.6,
        1.7
      ],
      "min_temp": [
        -8.0,
        -12.4,
        -16.3,
        -15.3,
        -5.4,
        -1.9,
        0.8
      ]
    },
    "ai_summary": "(idag): OBS idag kommer det pågå schaktning på skidstadion Vistas inte i närheten av maskinen. Håll avstånd på minst 20-30 m Konstsnöspåret ca 5 km K & F. Nypistat idag. 5 km gul K & F 10 km grön (ca 8 km K & F) Natursnöspåren prepareras med pistmaskin under gårdagen. Golfbanan 5 km K & F spårat med skoter och ginzugroomer under gårdagen.\n\n(1 dagar sedan): Konstsnöspåret drygt 3 km K & F. Postades sent onsdag kväll. 5 km gul K & F 10 km grön (ca 8 km K & F) Natursnöspåren prepareras med pistmaskin under morgonen. Golfbanan 5 km K & F spårat med skoter och ginzugroomer.",
    "official_url": "https://www.ulricehamn.se/uppleva-och-gora/bad-idrott-och-friluftsliv/hallar-och-idrottsanlaggningar/lassalyckan---centrum-for-idrott-och-friluftsliv/",
    "skidspar_url": "https://www.skidspar.se/vastra-gotaland/ulricehamn/lassalyckans-skidstadion",
    "webcam_url": "https://www.ipcamlive.com/66f2c680aac9d",
    "tags": [
      "konstsnö",
      "elljus",
      "wc",
      "dusch",
      "omklädningsrum"
    ],
    "phone": "0321-59 59 59",
    "total_track_length_km": 0,
    "ai_comments": [
      {
        "date": "2026-01-09T04:35:04.000Z",
        "days_ago": 0,
        "text": "OBS idag kommer det pågå schaktning på skidstadion Vistas inte i närheten av maskinen. Håll avstånd på minst 20-30 m Konstsnöspåret ca 5 km K & F. Nypistat idag. 5 km gul K & F 10 km grön (ca 8 km K & F) Natursnöspåren prepareras med pistmaskin under gårdagen. Golfbanan 5 km K & F spårat med skoter och ginzugroomer under gårdagen."
      },
      {
        "date": "2026-01-08T04:38:14.000Z",
        "days_ago": 1,
        "text": "Konstsnöspåret drygt 3 km K & F. Postades sent onsdag kväll. 5 km gul K & F 10 km grön (ca 8 km K & F) Natursnöspåren prepareras med pistmaskin under morgonen. Golfbanan 5 km K & F spårat med skoter och ginzugroomer."
      }
    ]
  },
  {
    "name": "Landvetter",
    "municipality": "Härryda",
    "lat": 57.708,
    "lon": 12.307,
    "status": "Troligen öppet",
    "snow_depth": "22 cm",
    "temperature": "-4°C",
    "last_update": "2026-01-09 17:03",
    "weather": "☀️ Klart",
    "forecast": {
      "dates": [
        "2026-01-09",
        "2026-01-10",
        "2026-01-11",
        "2026-01-12",
        "2026-01-13",
        "2026-01-14",
        "2026-01-15"
      ],
      "max_temp": [
        -3.5,
        -5.7,
        -6.7,
        -4.0,
        0.4,
        2.0,
        3.2
      ],
      "min_temp": [
        -8.1,
        -11.5,
        -16.8,
        -16.2,
        -3.7,
        0.4,
        1.1
      ]
    },
    "ai_summary": "(1 dagar sedan): Nyspårat på natursnöspåren, otroligt fint! Spår på både gamla och nya, den nykomna snön har gjort de något mjuka.\n\n(2 dagar sedan): Gamla och nya spåret pistade med ginzugroomern och fyrhjuling. Spår dragna längs det gamla elljusspåret med med relativt grund spårprofil. Men generellt väldigt fina förhållanden på Landehof!",
    "official_url": "https://oklandehof.se/",
    "skidspar_url": "https://www.skidspar.se/vastra-gotaland/harryda/landvetter",
    "webcam_url": null,
    "tags": [
      "konstsnö",
      "elljus"
    ],
    "phone": "-",
    "total_track_length_km": 0,
    "ai_comments": [
      {
        "date": "2026-01-08T12:07:10.000Z",
        "days_ago": 1,
        "text": "Nyspårat på natursnöspåren, otroligt fint! Spår på både gamla och nya, den nykomna snön har gjort de något mjuka."
      },
      {
        "date": "2026-01-07T15:29:15.000Z",
        "days_ago": 2,
        "text": "Gamla och nya spåret pistade med ginzugroomern och fyrhjuling. Spår dragna längs det gamla elljusspåret med med relativt grund spårprofil. Men generellt väldigt fina förhållanden på Landehof!"
      }
    ]
  },
  {
    "name": "Skidome Göteborg",
    "municipality": "Göteborg",
    "lat": 57.7089,
    "lon": 11.9746,
    "status": "Öppet",
    "snow_depth": "Konstsnö",
    "temperature": "-4°C",
    "last_update": "2026-01-09 17:04",
    "weather": "☀️ Klart",
    "forecast": {
      "dates": [
        "2026-01-09",
        "2026-01-10",
        "2026-01-11",
        "2026-01-12",
        "2026-01-13",
        "2026-01-14",
        "2026-01-15"
      ],
      "max_temp": [
        -2.4,
        -3.8,
        -5.5,
        -3.5,
        0.9,
        2.3,
        3.3
      ],
      "min_temp": [
        -6.0,
        -9.6,
        -16.9,
        -15.4,
        -3.3,
        0.9,
        1.2
      ]
    },
    "ai_summary": "Sammanfattning: Du kan hjälpa andra skidåkare genom att skapa en rapport för Skidome.",
    "official_url": "https://skidome.ski/",
    "skidspar_url": "https://www.skidspar.se/vastra-gotaland/goteborg/skidome",
    "webcam_url": null,
    "tags": [
      "inomhus",
      "konstsnö",
      "wc",
      "dusch",
      "omklädningsrum"
    ],
    "phone": "031-395 11 25",
    "total_track_length_km": 1.2,
    "ai_comments": []
  },
  {
    "name": "Billingen Skövde",
    "municipality": "Skövde",
    "lat": 58.4108,
    "lon": 13.8347,
    "status": "Troligen öppet",
    "snow_depth": "19 cm",
    "temperature": "-3°C",
    "last_update": "2026-01-09 17:04",
    "weather": "🌤️ Mestadels klart",
    "forecast": {
      "dates": [
        "2026-01-09",
        "2026-01-10",
        "2026-01-11",
        "2026-01-12",
        "2026-01-13",
        "2026-01-14",
        "2026-01-15"
      ],
      "max_temp": [
        -1.7,
        -5.8,
        -4.6,
        -5.4,
        -1.2,
        0.4,
        2.4
      ],
      "min_temp": [
        -8.2,
        -9.5,
        -13.2,
        -16.9,
        -5.6,
        -1.5,
        0.6
      ]
    },
    "ai_summary": "(idag): Hej! Idag fortsätter arbetet med att köra ut snö och iordningställa anläggningen. Så fort något är spårat så meddelar vi det här. Idag har vi gjort ett tappert försök att spåra Blängsmosse, men spåren blåser igen lika snabbt som vi spårar. Vi har därför plattat ifall någon tapper själ vill åka ut och göra ett spår med sina egna skidor. Trevlig tur önskar vi på Billingen\n\n(idag): Dagens tur med Anna Warner från SLA i -4 grader. Vi åkte Lasseslingan - kanonbra spår, några få genomslag men mycket bra spår. Ut och åk!!",
    "official_url": "https://billingenskovde.se/",
    "skidspar_url": "https://www.skidspar.se/vastra-gotaland/skovde/billingen-skovde",
    "webcam_url": "https://webcam.billingen.se/",
    "tags": [
      "konstsnö",
      "elljus",
      "wc",
      "dusch",
      "omklädningsrum"
    ],
    "phone": "0500-49 80 00",
    "total_track_length_km": 0,
    "ai_comments": [
      {
        "date": "2026-01-09T15:06:23.000Z",
        "days_ago": 0,
        "text": "Hej! Idag fortsätter arbetet med att köra ut snö och iordningställa anläggningen. Så fort något är spårat så meddelar vi det här. Idag har vi gjort ett tappert försök att spåra Blängsmosse, men spåren blåser igen lika snabbt som vi spårar. Vi har därför plattat ifall någon tapper själ vill åka ut och göra ett spår med sina egna skidor. Trevlig tur önskar vi på Billingen"
      },
      {
        "date": "2026-01-09T09:17:46.000Z",
        "days_ago": 0,
        "text": "Dagens tur med Anna Warner från SLA i -4 grader. Vi åkte Lasseslingan - kanonbra spår, några få genomslag men mycket bra spår. Ut och åk!!"
      }
    ]
  },
  {
    "name": "Borås Skidstadion",
    "municipality": "Borås",
    "lat": 57.721,
    "lon": 12.9401,
    "status": "Troligen öppet",
    "snow_depth": "18 cm",
    "temperature": "-4°C",
    "last_update": "2026-01-09 17:05",
    "weather": "☀️ Klart",
    "forecast": {
      "dates": [
        "2026-01-09",
        "2026-01-10",
        "2026-01-11",
        "2026-01-12",
        "2026-01-13",
        "2026-01-14",
        "2026-01-15"
      ],
      "max_temp": [
        -3.3,
        -5.5,
        -4.7,
        -5.1,
        -1.0,
        1.0,
        2.0
      ],
      "min_temp": [
        -6.1,
        -9.4,
        -16.5,
        -16.4,
        -4.7,
        -1.1,
        1.1
      ]
    },
    "ai_summary": "(idag): OBS ingen skiduthyrning öppen i morgon. Vi har en stor ungdomstävling med ca 300 deltagare. För motionärer har vi en slinga på 1 km öppen.\n\n(idag): Nyspårat klassiskt/skate hela banan . Vi har nu 3.3km. Vi stänger av hela övre delen av banan 20.00 Fredag kväll för förberedelser av Ungdomstävling. /välkomna",
    "official_url": "https://www.boras.se/upplevaochgora/friluftslivochnatur/skidspar.4.3aeb29ca158525e982c82ed8.html",
    "skidspar_url": "https://www.skidspar.se/vastra-gotaland/boras/boras-skidstadion",
    "webcam_url": null,
    "tags": [
      "konstsnö",
      "elljus",
      "wc",
      "dusch",
      "omklädningsrum"
    ],
    "phone": "033-35 73 73",
    "total_track_length_km": 0,
    "ai_comments": [
      {
        "date": "2026-01-09T14:46:08.000Z",
        "days_ago": 0,
        "text": "OBS ingen skiduthyrning öppen i morgon. Vi har en stor ungdomstävling med ca 300 deltagare. För motionärer har vi en slinga på 1 km öppen."
      },
      {
        "date": "2026-01-09T01:26:42.000Z",
        "days_ago": 0,
        "text": "Nyspårat klassiskt/skate hela banan . Vi har nu 3.3km. Vi stänger av hela övre delen av banan 20.00 Fredag kväll för förberedelser av Ungdomstävling. /välkomna"
      }
    ]
  },
  {
    "name": "Hestrastugan",
    "municipality": "Borås",
    "lat": 57.737,
    "lon": 12.915,
    "status": "Troligen öppet",
    "snow_depth": "19 cm",
    "temperature": "-5°C",
    "last_update": "2026-01-09 17:05",
    "weather": "☀️ Klart",
    "forecast": {
      "dates": [
        "2026-01-09",
        "2026-01-10",
        "2026-01-11",
        "2026-01-12",
        "2026-01-13",
        "2026-01-14",
        "2026-01-15"
      ],
      "max_temp": [
        -4.3,
        -6.3,
        -5.5,
        -5.0,
        -1.0,
        1.0,
        1.9
      ],
      "min_temp": [
        -7.2,
        -10.2,
        -16.1,
        -14.3,
        -4.8,
        -1.2,
        1.1
      ]
    },
    "ai_summary": "(idag): Kalasfina förhållanden på gårdagens ungdomsträning med Hestra's skidjuniorer! Hård och jämn skejtbädd med bra grepp, t.o.m ute på första ängs-spåret. Nya sträckningen gav fina förutsättningar för långa härliga backintervaller från botten av 5-vägskorset hela vägen upp till högsta punkten. Tack ALLA inblandade snögubbar o pistörer! 💥💥💥💥💥\n\n(idag): Då är hela nya konstsnö spåret preparerat för klassiskt o skate❄️.Så varmt välkomna att åka vara konstsnö som naturspår🤗. Spårpatrullen😄",
    "official_url": "https://hestraif.se/",
    "skidspar_url": "https://www.skidspar.se/vastra-gotaland/boras/hestrastugan",
    "webcam_url": null,
    "tags": [
      "konstsnö",
      "elljus"
    ],
    "phone": "033-24 33 47",
    "total_track_length_km": 0,
    "ai_comments": [
      {
        "date": "2026-01-09T06:14:29.000Z",
        "days_ago": 0,
        "text": "Kalasfina förhållanden på gårdagens ungdomsträning med Hestra's skidjuniorer! Hård och jämn skejtbädd med bra grepp, t.o.m ute på första ängs-spåret. Nya sträckningen gav fina förutsättningar för långa härliga backintervaller från botten av 5-vägskorset hela vägen upp till högsta punkten. Tack ALLA inblandade snögubbar o pistörer! 💥💥💥💥💥"
      },
      {
        "date": "2026-01-09T00:00:15.000Z",
        "days_ago": 0,
        "text": "Då är hela nya konstsnö spåret preparerat för klassiskt o skate❄️.Så varmt välkomna att åka vara konstsnö som naturspår🤗. Spårpatrullen😄"
      }
    ]
  },
  {
    "name": "Hindås",
    "municipality": "Härryda",
    "lat": 57.7036,
    "lon": 12.446,
    "status": "Troligen öppet",
    "snow_depth": "24 cm",
    "temperature": "-4°C",
    "last_update": "2026-01-09 17:05",
    "weather": "☀️ Klart",
    "forecast": {
      "dates": [
        "2026-01-09",
        "2026-01-10",
        "2026-01-11",
        "2026-01-12",
        "2026-01-13",
        "2026-01-14",
        "2026-01-15"
      ],
      "max_temp": [
        -3.4,
        -5.7,
        -6.1,
        -4.2,
        0.0,
        1.8,
        2.4
      ],
      "min_temp": [
        -8.1,
        -10.8,
        -18.0,
        -17.1,
        -4.0,
        0.0,
        1.1
      ]
    },
    "ai_summary": "(idag): Lägger med en bild på ängsspåret också. Blir ca 6km om man åker slingan såhär.\n\n(idag): Wow, nu är det fint på riktigt! Konstsnöspåret är nu spårat i sin fulla längd och bredd, nästan 3 km preparerat för skate och klassiskt. \"övre ängen\" med infart vid vägövergången. ca 3 km slinga för klassiskt och skate, några \"snälla genomslag\" i det klassiska spåret. Elljusspåret är också preparerat klassiskt och skate, se upp för genomslag i klassiska spåret där.",
    "official_url": "https://www.hindasskidklubb.se/startsida",
    "skidspar_url": "https://www.skidspar.se/vastra-gotaland/harryda/hindas",
    "webcam_url": null,
    "tags": [
      "natursnö",
      "elljus"
    ],
    "phone": "-",
    "total_track_length_km": 0,
    "ai_comments": [
      {
        "date": "2026-01-09T07:58:21.000Z",
        "days_ago": 0,
        "text": "Lägger med en bild på ängsspåret också. Blir ca 6km om man åker slingan såhär."
      },
      {
        "date": "2026-01-09T07:54:57.000Z",
        "days_ago": 0,
        "text": "Wow, nu är det fint på riktigt! Konstsnöspåret är nu spårat i sin fulla längd och bredd, nästan 3 km preparerat för skate och klassiskt. \"övre ängen\" med infart vid vägövergången. ca 3 km slinga för klassiskt och skate, några \"snälla genomslag\" i det klassiska spåret. Elljusspåret är också preparerat klassiskt och skate, se upp för genomslag i klassiska spåret där."
      }
    ]
  }
]